LICENSE
MANIFEST.in
README.md
requirements.txt
setup.py
faciesmapperpro/data_processor.py
faciesmapperpro/version.py
faciesmapperpro.egg-info/PKG-INFO
faciesmapperpro.egg-info/SOURCES.txt
faciesmapperpro.egg-info/dependency_links.txt
faciesmapperpro.egg-info/requires.txt
faciesmapperpro.egg-info/top_level.txt