Metadata-Version: 2.1
Name: faciesmapperpro
Version: 2.0.10
Summary: FaciesMapperPro aims to automate the process of facies interpretation in borehole images using deep learning techniques.                     The system is designed to be integrated with Techlog; a software platform developed by SLB for enabling the integration                     of all wellbore-centric data types into multi-discipline workflows including geological data analysis.                    In 2.0.10 I use concurrent programming and also modify the requirements.txt file for eas
Author: Srv
Author-email: smukherjee10@slb.com
Maintainer: Srv
Maintainer-email: smukherjee10@slb.com
License-File: LICENSE
